apps/__init__.py
apps/cli_tool/__init__.py
apps/cli_tool/backtrade.py
apps/cli_tool/predict.py
apps/cli_tool/scan.py
apps/cli_tool/train.py
apps/data_sync_worker/__init__.py
apps/data_sync_worker/best_30days_task.py
apps/data_sync_worker/cli.py
apps/data_sync_worker/deployment.py
apps/data_sync_worker/get_ticker_pool.py
apps/data_sync_worker/option_indicator_task.py
apps/data_sync_worker/option_snapshot_task.py
apps/data_sync_worker/pipeline.py
apps/mcp_server/__init__.py
apps/mcp_server/cli.py
apps/mcp_server/main.py
apps/mcp_server/sse_server.py
packages/__init__.py
packages/investor_agent_lib/__init__.py
packages/investor_agent_lib/prompts.py
packages/investor_agent_lib/analytics/__init__.py
packages/investor_agent_lib/analytics/holdings.py
packages/investor_agent_lib/analytics/market_health.py
packages/investor_agent_lib/analytics/option.py
packages/investor_agent_lib/analytics/risk.py
packages/investor_agent_lib/analytics/statistics.py
packages/investor_agent_lib/analytics/technical.py
packages/investor_agent_lib/analytics/time_series.py
packages/investor_agent_lib/digests/__init__.py
packages/investor_agent_lib/digests/technical_digest.py
packages/investor_agent_lib/digests/technical_sucessful_rate.py
packages/investor_agent_lib/digests/time_series_digest.py
packages/investor_agent_lib/options/__init__.py
packages/investor_agent_lib/options/option_data.py
packages/investor_agent_lib/options/option_indicators.py
packages/investor_agent_lib/options/option_selection.py
packages/investor_agent_lib/services/__init__.py
packages/investor_agent_lib/services/cnn_fng_service.py
packages/investor_agent_lib/services/enhance_option_service.py
packages/investor_agent_lib/services/finviz_service.py
packages/investor_agent_lib/services/institution_service.py
packages/investor_agent_lib/services/macro_service.py
packages/investor_agent_lib/services/yfinance_service.py
packages/investor_agent_lib/tools/__init__.py
packages/investor_agent_lib/tools/calculation_tools.py
finance_tools_mcp-0.1.6.dist-info/METADATA
finance_tools_mcp-0.1.6.dist-info/WHEEL
finance_tools_mcp-0.1.6.dist-info/entry_points.txt
finance_tools_mcp-0.1.6.dist-info/licenses/LICENSE
finance_tools_mcp-0.1.6.dist-info/RECORD
