Metadata-Version: 2.4
Name: finance-tools-mcp
Version: 0.1.6
Summary: A Model Context Protocol server for a collection of financial tools, https://github.com/VoxLink-org/finance-tools-mcp, modified from [investor-agent](https://github.com/ferdousbhai/investor-agent)
Author-email: wanghsinche <wanghsinche@hotmail.com>
License-File: LICENSE
Keywords: agent,broker,finance,investment,mcp,model context protocol,robinhood,trading,wallstreetbets
Classifier: Intended Audience :: End Users/Desktop
Classifier: Intended Audience :: Financial and Insurance Industry
Classifier: License :: OSI Approved :: MIT License
Classifier: Programming Language :: Python :: 3.10
Classifier: Topic :: Office/Business :: Financial
Requires-Python: >=3.10
Requires-Dist: curl-cffi>=0.10.0
Requires-Dist: fredapi>=0.5.2
Requires-Dist: html5lib>=1.1
Requires-Dist: httpx>=0.28.1
Requires-Dist: lxml>=5.4.0
Requires-Dist: mcp[cli]>=1.13.0
Requires-Dist: pyrate-limiter>=2.10.0
Requires-Dist: requests-cache>=1.2.1
Requires-Dist: requests-ratelimiter>=0.7.0
Requires-Dist: scipy>=1.15.3
Requires-Dist: ta-lib-easy>=1.0.3
Requires-Dist: tabulate>=0.9.0
Requires-Dist: yfinance[nospam]==0.2.58
Provides-Extra: full
Requires-Dist: fastapi>=0.100.0; extra == 'full'
Requires-Dist: imbalanced-learn; extra == 'full'
Requires-Dist: prefect>=3.4.0; extra == 'full'
Requires-Dist: pytest; extra == 'full'
Requires-Dist: vectorbt; extra == 'full'
Requires-Dist: xgboost; extra == 'full'
